LICENSE
MANIFEST.in
README.rst
VERSION
setup.py
fabops.egg-info/PKG-INFO
fabops.egg-info/SOURCES.txt
fabops.egg-info/dependency_links.txt
fabops.egg-info/top_level.txt
src/fabops/__init__.py
src/fabops/commands/__init__.py
src/fabops/commands/appengine.py
src/fabops/commands/clean.py
src/fabops/commands/django.py
src/fabops/commands/docs.py
src/fabops/commands/frontend.py
src/fabops/commands/git.py
src/fabops/commands/lint.py
src/fabops/commands/ops.py
src/fabops/commands/release.py
src/fabops/commands/test.py
src/fabops/commands/common/__init__.py
src/fabops/commands/common/conf.py
src/fabops/commands/common/fs.py
src/fabops/commands/common/git.py
src/fabops/commands/common/log.py
src/fabops/commands/common/project.py
src/fabops/commands/common/version.py