Metadata-Version: 1.1
Name: fabops
Version: 0.9.12
Summary: Set of fabric commands to help manage a project
Home-page: http://github.com/novopl/serafin
Author: Mateusz 'novo' Klos
Author-email: novopl@gmail.com
License: MIT
Keywords: fabric ops devops
Platform: UNKNOWN
Classifier: Development Status :: 4 - Beta
Classifier: Topic :: Utilities
Classifier: Intended Audience :: Developers
Classifier: Programming Language :: Python
Classifier: License :: OSI Approved :: MIT License
